dsch/__init__.py
dsch/data.py
dsch/exceptions.py
dsch/frontend.py
dsch/schema.py
dsch/storage.py
dsch/backends/__init__.py
dsch/backends/hdf5.py
dsch/backends/inmem.py
dsch/backends/mat.py
dsch/backends/npz.py
dsch-0.3.2.dist-info/AUTHORS.rst
dsch-0.3.2.dist-info/LICENSE
dsch-0.3.2.dist-info/METADATA
dsch-0.3.2.dist-info/WHEEL
dsch-0.3.2.dist-info/top_level.txt
dsch-0.3.2.dist-info/RECORD
