Metadata-Version: 2.1
Name: dsch
Version: 0.3.2
Summary: Structured, metadata-enhanced data storage.
Home-page: https://github.com/emtpb/dsch/
Author: Manuel Webersen
Author-email: webersen@emt.uni-paderborn.de
License: BSD
Classifier: Development Status :: 3 - Alpha
Classifier: Intended Audience :: Science/Research
Classifier: License :: OSI Approved :: BSD License
Classifier: Programming Language :: Python :: 3
Classifier: Topic :: Scientific/Engineering
Requires-Python: >=3
License-File: LICENSE
License-File: AUTHORS.rst
Requires-Dist: asciitree
Requires-Dist: numpy
Provides-Extra: hdf5
Requires-Dist: h5py ; extra == 'hdf5'
Provides-Extra: mat
Requires-Dist: scipy ; extra == 'mat'
